{"ygPerms":{"resourceCapabilityList":[{"resourceType":"GROUP","capabilities":[{"name":"READ"},{"name":"JOIN"}]},{"resourceType":"PHOTO","capabilities":[]},{"resourceType":"FILE","capabilities":[]},{"resourceType":"MEMBER","capabilities":[]},{"resourceType":"LINK","capabilities":[]},{"resourceType":"CALENDAR","capabilities":[]},{"resourceType":"DATABASE","capabilities":[]},{"resourceType":"POLL","capabilities":[]},{"resourceType":"MESSAGE","capabilities":[{"name":"READ"}]},{"resourceType":"PENDING_MESSAGE","capabilities":[]},{"resourceType":"ATTACHMENTS","capabilities":[{"name":"READ"}]},{"resourceType":"PHOTOMATIC_ALBUMS","capabilities":[]},{"resourceType":"MEMBERSHIP_TYPE","capabilities":[]},{"resourceType":"POST","capabilities":[{"name":"READ"}]},{"resourceType":"PIN","capabilities":[]}],"groupUrl":"groups.yahoo.com","intlCode":"us"},"comscore":"pageview_candidate","ygData":{"userId":136218993,"authorName":"Story Henry","from":"Story Henry &lt;henry.story@...&gt;","profile":"hjsatdoc","replyTo":"SENDER","senderId":"ZhIX0TU-WUHiC5gpfA26XejAx2ISnYLM2TVPexeHc2UhvPm_LuOWcu9elrNTYk1e_t3CTTxMGMRkV7VrLhkfAZEaD_mO7hWRYsjWKg","spamInfo":{"isSpam":false,"reason":"3"},"subject":"Re: [rest-discuss] REST for non-Web Applications","postDate":"1207143674","msgId":10586,"canDelete":false,"contentTrasformed":false,"systemMessage":false,"headers":{"messageIdInHeader":"PDFDMEYzRjBDLURFOEMtNEY2RC1CMjMxLTBDRTNDQTY3ODExOUBiYmxmaXNoLm5ldD4=","inReplyToHeader":"PGZ0MDF0dCtuamZrQGVHcm91cHMuY29tPg==","referencesHeader":"PGZ0MDF0dCtuamZrQGVHcm91cHMuY29tPg=="},"prevInTopic":10585,"nextInTopic":10587,"prevInTime":10585,"nextInTime":10587,"topicId":10584,"numMessagesInTopic":11,"msgSnippet":"It is a nice book, and I started reviewing it here http://blogs.sun.com/bblfish/entry/restful_web_services_the_book But really there is no reason it could not","rawEmail":"Return-Path: &lt;henry.story@...&gt;\r\nX-Sender: henry.story@...\r\nX-Apparently-To: rest-discuss@yahoogroups.com\r\nX-Received: (qmail 69809 invoked from network); 2 Apr 2008 13:41:25 -0000\r\nX-Received: from unknown (66.218.67.96)\n  by m55.grp.scd.yahoo.com with QMQP; 2 Apr 2008 13:41:25 -0000\r\nX-Received: from unknown (HELO zone5.gridzones.com) (69.90.133.49)\n  by mta17.grp.scd.yahoo.com with SMTP; 2 Apr 2008 13:41:24 -0000\r\nX-Received: from [192.168.0.10] (fbl77-1-88-163-3-25.fbx.proxad.net [88.163.3.25])\n\t(authenticated bits=0)\n\tby zone5.gridzones.com (8.13.8/8.13.7) with ESMTP id m32DfF1N004343\n\t(version=TLSv1/SSLv3 cipher=AES128-SHA bits=128 verify=NO);\n\tWed, 2 Apr 2008 06:41:17 -0700 (PDT)\r\nCc: rest-discuss@yahoogroups.com\r\nMessage-Id: &lt;1C0F3F0C-DE8C-4F6D-B231-0CE3CA678119@...&gt;\r\nTo: &quot;dfl_maradentro&quot; &lt;dfl_maradentro@...&gt;\r\nIn-Reply-To: &lt;ft01tt+njfk@...&gt;\r\nContent-Type: multipart/signed; boundary=Apple-Mail-160--944276112; micalg=sha1; protocol=&quot;application/pkcs7-signature&quot;\r\nMime-Version: 1.0 (Apple Message framework v919.2)\r\nDate: Wed, 2 Apr 2008 15:41:14 +0200\r\nReferences: &lt;ft01tt+njfk@...&gt;\r\nX-Mailer: Apple Mail (2.919.2)\r\nX-Virus-Scanned: ClamAV version 0.91.1, clamav-milter version 0.91.1 on zone5.gridzones.com\r\nX-Virus-Status: Clean\r\nX-eGroups-Msg-Info: 2:3:4:0:0\r\nFrom: Story Henry &lt;henry.story@...&gt;\r\nSubject: Re: [rest-discuss] REST for non-Web Applications\r\nX-Yahoo-Group-Post: member; u=136218993; y=YGyeBVIymst0TMaAthLrjHsuILIeIm-P8nknT95Yvm7Gi6Q\r\nX-Yahoo-Profile: hjsatdoc\r\n\r\n\r\n--Apple-Mail-160--944276112\r\nContent-Type: text/plain;\n\tcharset=US-ASCII;\n\tformat=flowed\r\nContent-Transfer-Encoding: 7bit\r\n\r\nIt is a nice book, and I started reviewing it here\n\nhttp://blogs.sun.com/bblfish/entry/restful_web_services_the_book\n\nBut really there is no reason it could not work with Linked Data\n\nhttp://en.wikipedia.org/wiki/Linked_Data\n\nIn fact ROA and RDF and REST are all designed to work together.\n\nHenry\n\nOn 2 Apr 2008, at 15:32, dfl_maradentro wrote:\n&gt; Hi you all,\n&gt;\n&gt; reading the book in [1], they say that, as REST is not only applicable\n&gt; to the Web, they propose a specific REST-based Web architecture, name\n&gt; ROA (Resource Oriented Architecture).\n&gt;\n&gt; If any of you have read this book, can anybody tell me why this\n&gt; architecture cannot be applied to any other hypermedia distributed\n&gt; environment?\n&gt;\n&gt; Thanks a lot.\n&gt;\n&gt; [1] Leonard Richardson and Sam Ruby, RESTful Web Services. O&#39;Reilly,\n&gt; mayo 2007\n&gt;\n\n\r\n--Apple-Mail-160--944276112\r\nContent-Disposition: attachment;\n\tfilename=smime.p7s\r\nContent-Type: application/pkcs7-signature;\n\tname=smime.p7s\r\n\r\n[ Attachment content not displayed ]\r\n--Apple-Mail-160--944276112--\r\n\n"}}