{"ygPerms":{"resourceCapabilityList":[{"resourceType":"GROUP","capabilities":[{"name":"READ"},{"name":"JOIN"}]},{"resourceType":"PHOTO","capabilities":[]},{"resourceType":"FILE","capabilities":[]},{"resourceType":"MEMBER","capabilities":[]},{"resourceType":"LINK","capabilities":[]},{"resourceType":"CALENDAR","capabilities":[]},{"resourceType":"DATABASE","capabilities":[]},{"resourceType":"POLL","capabilities":[]},{"resourceType":"MESSAGE","capabilities":[{"name":"READ"}]},{"resourceType":"PENDING_MESSAGE","capabilities":[]},{"resourceType":"ATTACHMENTS","capabilities":[{"name":"READ"}]},{"resourceType":"PHOTOMATIC_ALBUMS","capabilities":[]},{"resourceType":"MEMBERSHIP_TYPE","capabilities":[]},{"resourceType":"POST","capabilities":[{"name":"READ"}]},{"resourceType":"PIN","capabilities":[]}],"groupUrl":"groups.yahoo.com","intlCode":"us"},"comscore":"pageview_candidate","ygData":{"userId":63473576,"authorName":"Lucas Gonze","from":"&quot;Lucas Gonze&quot; &lt;lucas@...&gt;","profile":"lucas_gonze","replyTo":"SENDER","senderId":"wy7ZOT6JjBjmSgEs9viGsgyHVI_SFfldOY_57Qv6oA7iVNOBrEEkokYOed1mh1siS6KWlMqmRpwJpehh65GdHjiGEMsgNA","spamInfo":{"isSpam":false,"reason":"0"},"subject":"RE: [rest-discuss] a proposal for secure notifications","postDate":"1012163821","msgId":372,"canDelete":false,"contentTrasformed":false,"systemMessage":false,"headers":{"messageIdInHeader":"PE5FQkJKSUhNTUxLSEVPUE5PR0hEQ0VNSEZKQUEubHVjYXNAZ29uemUuY29tPg==","inReplyToHeader":"PDNDNTQ1RDM4LkI3NjFBNkU5QHByZXNjb2QubmV0Pg=="},"prevInTopic":370,"nextInTopic":374,"prevInTime":371,"nextInTime":373,"topicId":360,"numMessagesInTopic":23,"msgSnippet":"I note that PSP is, in practice, unidirectional.  :)","rawEmail":"Return-Path: &lt;lucas@...&gt;\r\nX-Sender: lucas@...\r\nX-Apparently-To: rest-discuss@yahoogroups.com\r\nReceived: (EGP: mail-8_0_1_3); 27 Jan 2002 20:37:56 -0000\r\nReceived: (qmail 98047 invoked from network); 27 Jan 2002 20:37:55 -0000\r\nReceived: from unknown (216.115.97.167)\n  by m11.grp.snv.yahoo.com with QMQP; 27 Jan 2002 20:37:55 -0000\r\nReceived: from unknown (HELO mail2.panix.com) (166.84.0.213)\n  by mta1.grp.snv.yahoo.com with SMTP; 27 Jan 2002 20:37:55 -0000\r\nReceived: from lucas (159-98.nyc.dsl.access.net [166.84.159.98])\n\tby mail2.panix.com (Postfix) with SMTP\n\tid 9E5BB8EA3; Sun, 27 Jan 2002 15:37:54 -0500 (EST)\r\nTo: &quot;Paul Prescod&quot; &lt;paul@...&gt;,\n\t&quot;Rest-Discuss&quot; &lt;rest-discuss@yahoogroups.com&gt;\r\nSubject: RE: [rest-discuss] a proposal for secure notifications\r\nDate: Sun, 27 Jan 2002 15:37:01 -0500\r\nMessage-ID: &lt;NEBBJIHMMLKHEOPNOGHDCEMHFJAA.lucas@...&gt;\r\nMIME-Version: 1.0\r\nContent-Type: text/plain;\n\tcharset=&quot;iso-8859-1&quot;\r\nContent-Transfer-Encoding: 7bit\r\nX-Priority: 3 (Normal)\r\nX-MSMail-Priority: Normal\r\nX-Mailer: Microsoft Outlook IMO, Build 9.0.2416 (9.0.2910.0)\r\nIn-Reply-To: &lt;3C545D38.B761A6E9@...&gt;\r\nX-MimeOLE: Produced By Microsoft MimeOLE V5.00.2919.6600\r\nImportance: Normal\r\nFrom: &quot;Lucas Gonze&quot; &lt;lucas@...&gt;\r\nX-Yahoo-Group-Post: member; u=63473576\r\nX-Yahoo-Profile: lucas_gonze\r\n\r\nI note that PSP is, in practice, unidirectional.  :)\n\n&gt; The care and thought put into your PSP won&#39;t mean squat to a corporate\n&gt; sysadmin. And on reflection I do think that practically speaking,\n&gt; unidirectional connections provide more safety than paranoid protocol\n&gt; implementations. And anyhow, it is pretty easy to set up a single\n&gt; unidirectional connection to your &quot;event server&quot; on the Web and let it\n&gt; handle the security crap for you.\n&gt; \n&gt;  Paul Prescod\n\n\n"}}