{"ygPerms":{"resourceCapabilityList":[{"resourceType":"GROUP","capabilities":[{"name":"READ"},{"name":"JOIN"}]},{"resourceType":"PHOTO","capabilities":[]},{"resourceType":"FILE","capabilities":[]},{"resourceType":"MEMBER","capabilities":[]},{"resourceType":"LINK","capabilities":[]},{"resourceType":"CALENDAR","capabilities":[]},{"resourceType":"DATABASE","capabilities":[]},{"resourceType":"POLL","capabilities":[]},{"resourceType":"MESSAGE","capabilities":[{"name":"READ"}]},{"resourceType":"PENDING_MESSAGE","capabilities":[]},{"resourceType":"ATTACHMENTS","capabilities":[{"name":"READ"}]},{"resourceType":"PHOTOMATIC_ALBUMS","capabilities":[]},{"resourceType":"MEMBERSHIP_TYPE","capabilities":[]},{"resourceType":"POST","capabilities":[{"name":"READ"}]},{"resourceType":"PIN","capabilities":[]}],"groupUrl":"groups.yahoo.com","intlCode":"us"},"comscore":"pageview_candidate","ygData":{"userId":189321215,"authorName":"Alan Dean","from":"&quot;Alan Dean&quot; &lt;alan.dean@...&gt;","profile":"alan_james_dean","replyTo":"SENDER","senderId":"xK_gsx0KSzd-voQhcqx6DdiZTymuCDKncssi_kroplX4xP70DUL-_NmLmRKWCpO5-X7pB2vU7WpETZ5XLPqEki_pZyLEe-hT","spamInfo":{"isSpam":false,"reason":"0"},"subject":"Re: [rest-discuss] Re: Acceptable Responses","postDate":"1173108902","msgId":8081,"canDelete":false,"contentTrasformed":false,"systemMessage":false,"headers":{"messageIdInHeader":"PDZmYjE3M2Y1MDcwMzA1MDczNWpjZWYxYmRieWYwZmI4MzIxYzgwZTBjNDlAbWFpbC5nbWFpbC5jb20+","inReplyToHeader":"PGVzaGMzOSttMmdoQGVHcm91cHMuY29tPg==","referencesHeader":"PGVzaDdqMiR2cHQkMUBzZWEuZ21hbmUub3JnPiA8ZXNoYzM5K20yZ2hAZUdyb3Vwcy5jb20+"},"prevInTopic":8080,"nextInTopic":8082,"prevInTime":8080,"nextInTime":8082,"topicId":8074,"numMessagesInTopic":13,"msgSnippet":"... Just to be clear - the Accept header is defined as a Request header and so cannot be used in the response. My idea is to use a new Response header called","rawEmail":"Return-Path: &lt;alan.dean@...&gt;\r\nX-Sender: alan.dean@...\r\nX-Apparently-To: rest-discuss@yahoogroups.com\r\nReceived: (qmail 24714 invoked from network); 5 Mar 2007 15:35:07 -0000\r\nReceived: from unknown (66.218.66.72)\n  by m49.grp.scd.yahoo.com with QMQP; 5 Mar 2007 15:35:07 -0000\r\nReceived: from unknown (HELO an-out-0708.google.com) (209.85.132.248)\n  by mta14.grp.scd.yahoo.com with SMTP; 5 Mar 2007 15:35:07 -0000\r\nReceived: by an-out-0708.google.com with SMTP id d26so1420315and\n        for &lt;rest-discuss@yahoogroups.com&gt;; Mon, 05 Mar 2007 07:35:02 -0800 (PST)\r\nDKIM-Signature: a=rsa-sha1; c=relaxed/relaxed;\n        d=gmail.com; s=beta;\n        h=domainkey-signature:received:received:message-id:date:from:to:subject:in-reply-to:mime-version:content-type:content-transfer-encoding:content-disposition:references;\n        b=sk+ER3n1HxdzIclfjeJT1R9GN8hTCE2G/2SB62iFakSAYxwSNWA3hoVQ0k9DW75pFYfIpX2cU8IjJzX+m2RgwhawRdmfNMR+hxFgb1/CFpC0tsV8HKfhvAeuogpqBdhIVdEBV5hwNP1XHOW1YBrqBimbX8eIQ4BkK3mQJAYl9K8=\r\nReceived: by 10.100.138.2 with SMTP id l2mr4339854and.1173108902189;\n        Mon, 05 Mar 2007 07:35:02 -0800 (PST)\r\nReceived: by 10.100.151.8 with HTTP; Mon, 5 Mar 2007 07:35:02 -0800 (PST)\r\nMessage-ID: &lt;6fb173f50703050735jcef1bdbyf0fb8321c80e0c49@...&gt;\r\nDate: Mon, 5 Mar 2007 15:35:02 +0000\r\nTo: rest-discuss@yahoogroups.com\r\nIn-Reply-To: &lt;eshc39+m2gh@...&gt;\r\nMIME-Version: 1.0\r\nContent-Type: text/plain; charset=UTF-8; format=flowed\r\nContent-Transfer-Encoding: 7bit\r\nContent-Disposition: inline\r\nReferences: &lt;esh7j2$vpt$1@...&gt; &lt;eshc39+m2gh@...&gt;\r\nX-eGroups-Msg-Info: 1:0:0:0\r\nFrom: &quot;Alan Dean&quot; &lt;alan.dean@...&gt;\r\nSubject: Re: [rest-discuss] Re: Acceptable Responses\r\nX-Yahoo-Group-Post: member; u=189321215; y=yVf_ILIL-0k614jp5RSKlgfNU5OydRsdXc_Zk0sBok3Ob4vRaVggRDWH\r\nX-Yahoo-Profile: alan_james_dean\r\n\r\nOn 3/5/07, wahbedahbe &lt;andrew.wahbe@...&gt; wrote:\n&gt;\n&gt; On re-using Accept in the response:\n&gt;\n&gt; For what its worth, SIP uses an Accept in the OPTIONS response to\n&gt; indicate what types the resource itself can accept in requests.\n&gt;\n&gt; It makes sense that this would mean the same thing in the context of\n&gt; HTTP. ie. this is what can be POSTed or PUT to the resource.\n\nJust to be clear - the Accept header is defined as a Request header\nand so cannot be used in the response.\n\nMy idea is to use a new Response header called Acceptable to provide a\nlist of supported Content-Types to the client.\n\n(Of course, unless it was formalised - it should be X-Acceptable)\n\nAlan\n\n"}}