{"ygPerms":{"resourceCapabilityList":[{"resourceType":"GROUP","capabilities":[{"name":"READ"},{"name":"JOIN"}]},{"resourceType":"PHOTO","capabilities":[]},{"resourceType":"FILE","capabilities":[]},{"resourceType":"MEMBER","capabilities":[]},{"resourceType":"LINK","capabilities":[]},{"resourceType":"CALENDAR","capabilities":[]},{"resourceType":"DATABASE","capabilities":[]},{"resourceType":"POLL","capabilities":[]},{"resourceType":"MESSAGE","capabilities":[{"name":"READ"}]},{"resourceType":"PENDING_MESSAGE","capabilities":[]},{"resourceType":"ATTACHMENTS","capabilities":[{"name":"READ"}]},{"resourceType":"PHOTOMATIC_ALBUMS","capabilities":[]},{"resourceType":"MEMBERSHIP_TYPE","capabilities":[]},{"resourceType":"POST","capabilities":[{"name":"READ"}]},{"resourceType":"PIN","capabilities":[]}],"groupUrl":"groups.yahoo.com","intlCode":"us"},"comscore":"pageview_candidate","ygData":{"userId":266460716,"authorName":"Eric J. Bowman","from":"&quot;Eric J. Bowman&quot; &lt;eric@...&gt;","replyTo":"SENDER","senderId":"TNIi8BND0Xu7415RJTvDZKPlkba8yGFwjYRtNnTNqLVnHRC1JAKfIyc0opcz0JQgnFeA9vhaRAqsbp2MOHZ4Q5lmb3eg6x_WRruoFDjWWA","spamInfo":{"isSpam":false,"reason":"0"},"subject":"Bass-ackwards?","postDate":"1178940771","msgId":8412,"canDelete":false,"contentTrasformed":false,"systemMessage":false,"headers":{"messageIdInHeader":"PFc0MDE0NTI5Nzc0MzA3MjUxMTc4OTQwNzcxQG1haWwubWFpbHNuYXJlLm5ldD4="},"prevInTopic":0,"nextInTopic":8413,"prevInTime":8411,"nextInTime":8413,"topicId":8412,"numMessagesInTopic":22,"msgSnippet":"Has Microsoft s Windows Live Contacts API confused PUT and POST? [1] http://msdn2.microsoft.com/en-us/library/bb447763.aspx [2]","rawEmail":"Return-Path: &lt;eric@...&gt;\r\nX-Sender: eric@...\r\nX-Apparently-To: rest-discuss@yahoogroups.com\r\nReceived: (qmail 43801 invoked from network); 12 May 2007 04:57:30 -0000\r\nReceived: from unknown (66.218.67.33)\n  by m45.grp.scd.yahoo.com with QMQP; 12 May 2007 04:57:29 -0000\r\nReceived: from unknown (HELO ev2.mailsnare.net) (70.85.220.194)\n  by mta7.grp.scd.yahoo.com with SMTP; 12 May 2007 04:57:29 -0000\r\nX-Virus-Scanned: by ClamAV at mailsnare.net\r\nX-Message-ID: 749f92e98ac7daa1b40c7093adeba4681e7bd0d5869d272e49d9ebde58f8da29\r\nReceived: from mail.mailsnare.net (unknown [209.236.228.74])\n\tby mail.mailsnare.net (Postfix) with ESMTP id 6887A51B37\n\tfor &lt;rest-discuss@yahoogroups.com&gt;; Sat, 12 May 2007 05:00:46 +0000 (UTC)\r\nTo: rest-discuss@yahoogroups.com\r\nImportance: Normal\r\nSensitivity: Normal\r\nMessage-ID: &lt;W4014529774307251178940771@...&gt;\r\nX-Mailer: Mintersoft EdgeDesk, Build 4.03.0105\r\nDate: Sat, 12 May 2007 03:32:51 +0000\r\nOrganization: Bison Systems Corporation\r\nMIME-Version: 1.0\r\nContent-Type: text/plain; charset=&quot;utf-8&quot;\r\nContent-Transfer-Encoding: 7bit\r\nX-eGroups-Msg-Info: 1:0:0:0\r\nFrom: &quot;Eric J. Bowman&quot; &lt;eric@...&gt;\r\nReply-To: eric@...\r\nSubject: Bass-ackwards?\r\nX-Yahoo-Group-Post: member; u=266460716\r\n\r\nHas Microsoft&#39;s &quot;Windows Live Contacts API&quot; confused PUT and POST?\n\n[1] http://msdn2.microsoft.com/en-us/library/bb447763.aspx\n[2] http://msdn2.microsoft.com/en-us/library/bb463980.aspx\n\nSpecifically, isn&#39;t [1] a fine example of how not to use PUT?  The \nfirst example on [2] looks like a job for PUT, although POST is OK too, \nI guess.  The example given at the bottom of [2] looks like a valid use \nof POST, but change method to PUT and you&#39;re back at square [1], right?\n\n-Eric\n\n[3] http://msdn2.microsoft.com/en-us/library/bb463982.aspx\n\n\n\n"}}